README.txt
setup.py
wdt/__init__.py
wdt/dt/__init__.py
wdt/dt/devtools_jstable.py
wdt/dt/devtools_params.py
wdt/dt/devtools_preset.py
wdt/images/wialon.png
wdt/ips/__init__.py
wdt/ips/wialon_ips_client.py
wdt/ips/wialon_ips_page.py
wdt/presets/requests.preset
wdt/presets/settings.preset
wdt/remote_api/__init__.py
wdt/remote_api/remote_api_page.py
wdt/remote_api/requests_page.py
wdt/remote_api/settings_page.py
wdt/remote_api/wialon_sdk_client.py
wialon_devtools.egg-info/PKG-INFO
wialon_devtools.egg-info/SOURCES.txt
wialon_devtools.egg-info/dependency_links.txt
wialon_devtools.egg-info/entry_points.txt
wialon_devtools.egg-info/requires.txt
wialon_devtools.egg-info/top_level.txt