Metadata-Version: 1.0
Name: wialon-devtools
Version: 1.1.0
Summary: Wialon Devtools
Home-page: https://github.com/shevast/wialon_devtools
Author: Sergey Shevchik
Author-email: sergey.shevchik@gmail.com
License: UNKNOWN
Platform: UNKNOWN
